pyarcamsolo/__init__.py
pyarcamsolo/_version.py
pyarcamsolo/commands.py
pyarcamsolo/params.py
pyarcamsolo/parser.py
pyarcamsolo/util.py
pyarcamsolo-0.2.1.dist-info/licenses/LICENSE
pyarcamsolo-0.2.1.dist-info/METADATA
pyarcamsolo-0.2.1.dist-info/WHEEL
pyarcamsolo-0.2.1.dist-info/entry_points.txt
pyarcamsolo-0.2.1.dist-info/top_level.txt
pyarcamsolo-0.2.1.dist-info/RECORD
