Metadata-Version: 2.4
Name: pyarcamsolo
Version: 0.2.1
Summary: Asyncio Python library for controlling Arcam Solo Hi-Fi devices via RS232 ser2net bridge.
Home-page: http://github.com/pantherale0/pyarcamsolo
Author: pantherale0
License: MIT
Classifier: Framework :: AsyncIO
Classifier: Intended Audience :: Developers
Classifier: Topic :: Home Automation
Classifier: Topic :: Software Development :: Libraries :: Python Modules
Classifier: Programming Language :: Python :: 3
Classifier: License :: OSI Approved :: MIT License
Classifier: Operating System :: OS Independent
Requires-Python: >=3.8, <4
License-File: LICENSE
Requires-Dist: pyserial-asyncio-fast==0.*
Requires-Dist: pyserial==3.*
Provides-Extra: dev
Requires-Dist: bandit==1.7.*; extra == "dev"
Requires-Dist: black==23.*; extra == "dev"
Requires-Dist: build==0.10.*; extra == "dev"
Requires-Dist: flake8==6.*; extra == "dev"
Requires-Dist: isort==5.*; extra == "dev"
Requires-Dist: mypy==1.5.*; extra == "dev"
Requires-Dist: pytest==7.*; extra == "dev"
Requires-Dist: pytest-cov==4.*; extra == "dev"
Requires-Dist: twine==4.*; extra == "dev"
Dynamic: author
Dynamic: classifier
Dynamic: description
Dynamic: description-content-type
Dynamic: home-page
Dynamic: license
Dynamic: license-file
Dynamic: provides-extra
Dynamic: requires-dist
Dynamic: requires-python
Dynamic: summary
